squaredinc_sdk/__init__.py
squaredinc_sdk/client.py
squaredinc_sdk-0.2.0.dist-info/METADATA
squaredinc_sdk-0.2.0.dist-info/WHEEL
squaredinc_sdk-0.2.0.dist-info/top_level.txt
squaredinc_sdk-0.2.0.dist-info/RECORD
